MANIFEST.in
README.rst
setup.py
docs/.gitattributes
docs/HISTORY.txt
docs/LICENSE.GPL
docs/LICENSE.txt
docs/manage-upgrades.png
ftw/__init__.py
ftw.upgrade.egg-info/PKG-INFO
ftw.upgrade.egg-info/SOURCES.txt
ftw.upgrade.egg-info/dependency_links.txt
ftw.upgrade.egg-info/entry_points.txt
ftw.upgrade.egg-info/namespace_packages.txt
ftw.upgrade.egg-info/not-zip-safe
ftw.upgrade.egg-info/requires.txt
ftw.upgrade.egg-info/top_level.txt
ftw/upgrade/__init__.py
ftw/upgrade/configure.zcml
ftw/upgrade/events.py
ftw/upgrade/exceptions.py
ftw/upgrade/executioner.py
ftw/upgrade/gatherer.py
ftw/upgrade/helpers.py
ftw/upgrade/indexing.py
ftw/upgrade/interfaces.py
ftw/upgrade/meta.zcml
ftw/upgrade/migration.py
ftw/upgrade/placefulworkflow.py
ftw/upgrade/progresslogger.py
ftw/upgrade/resource_registries.py
ftw/upgrade/step.py
ftw/upgrade/testing.py
ftw/upgrade/transactionnote.py
ftw/upgrade/utils.py
ftw/upgrade/workflow.py
ftw/upgrade/zcml.py
ftw/upgrade/browser/__init__.py
ftw/upgrade/browser/configure.zcml
ftw/upgrade/browser/manage.py
ftw/upgrade/browser/resources/icon.png
ftw/upgrade/browser/resources/manage.css
ftw/upgrade/browser/resources/manage.js
ftw/upgrade/browser/resources/orphan.png
ftw/upgrade/browser/resources/upgrade-deferrable.png
ftw/upgrade/browser/resources/upgrade-error.png
ftw/upgrade/browser/resources/upgrade-installed.png
ftw/upgrade/browser/resources/upgrade-outdated-fs-version.png
ftw/upgrade/browser/resources/upgrade-proposed.png
ftw/upgrade/browser/templates/manage.pt
ftw/upgrade/browser/templates/manage_plain.pt
ftw/upgrade/command/__init__.py
ftw/upgrade/command/create.py
ftw/upgrade/command/formatter.py
ftw/upgrade/command/help.py
ftw/upgrade/command/install.py
ftw/upgrade/command/jsonapi.py
ftw/upgrade/command/list_cmd.py
ftw/upgrade/command/plone_upgrade.py
ftw/upgrade/command/plone_upgrade_needed.py
ftw/upgrade/command/recook.py
ftw/upgrade/command/sites.py
ftw/upgrade/command/terminal.py
ftw/upgrade/command/touch.py
ftw/upgrade/command/user.py
ftw/upgrade/command/utils.py
ftw/upgrade/directory/__init__.py
ftw/upgrade/directory/recorder.py
ftw/upgrade/directory/scaffold.py
ftw/upgrade/directory/scanner.py
ftw/upgrade/directory/subscribers.py
ftw/upgrade/directory/wrapper.py
ftw/upgrade/directory/zcml.py
ftw/upgrade/intid/__init__.py
