Metadata-Version: 1.1
Name: ftw.upgrade
Version: 2.12.1
Summary: An upgrade control panel and upgrade helpers for plone upgrades.
Home-page: https://github.com/4teamwork/ftw.upgrade
Author: 4teamwork AG
Author-email: mailto:info@4teamwork.ch
License: GPL2
Keywords: plone ftw upgrade
Platform: UNKNOWN
Classifier: Framework :: Plone
Classifier: Framework :: Plone :: 4.3
Classifier: Framework :: Plone :: 5.1
Classifier: Intended Audience :: Developers
Classifier: License :: OSI Approved :: GNU General Public License (GPL)
Classifier: Programming Language :: Python
Classifier: Topic :: Software Development
